{
  "generatedAt": "2026-06-26T06:20:00.000Z",
  "project": "TxODDS World Cup Sentinel",
  "mode": "demo-data",
  "purpose": "Replay package for Superteam/TxODDS judges to verify the public MVP without private keys, API tokens, wallet signing, or live network calls.",
  "urls": {
    "liveMvp": "https://txodds-worldcup-sentinel.vercel.app",
    "publicRepository": "https://github.com/chico10117/txodds-worldcup-sentinel",
    "demoVideoPage": "https://txodds-worldcup-sentinel.vercel.app/demo-video.html",
    "judgePlayground": "https://txodds-worldcup-sentinel.vercel.app/judge-playground.html",
    "judgeBrief": "https://txodds-worldcup-sentinel.vercel.app/judge-brief.html",
    "compliance": "https://txodds-worldcup-sentinel.vercel.app/compliance.html",
    "aiTxt": "https://txodds-worldcup-sentinel.vercel.app/.well-known/ai.txt",
    "demoVideo": "https://github.com/chico10117/txodds-worldcup-sentinel/blob/main/media/demo.mp4",
    "reportJson": "https://txodds-worldcup-sentinel.vercel.app/report.json",
    "txoddsCaptureReportJson": "https://txodds-worldcup-sentinel.vercel.app/txodds-capture-report.json",
    "replayManifestJson": "https://txodds-worldcup-sentinel.vercel.app/replay-manifest.json"
  },
  "commands": [
    "npm test",
    "npm run build",
    "npm run build:video",
    "npm run report:txodds",
    "npm run verify:packet",
    "npm run verify:ci",
    "node src/cli.js fixtures/sample-worldcup-feed.json --now 2026-06-26T06:20:00.000Z",
    "node src/cli.js fixtures/sample-txodds-capture.json --input-format txodds --now 2026-06-26T06:20:00.000Z"
  ],
  "reports": {
    "fixture": {
      "generatedAt": "2026-06-26T06:20:00.000Z",
      "matchCount": 2,
      "marketCount": 2,
      "flagCount": 10,
      "riskScore": 35,
      "recommendedActionCount": 4,
      "automationReadinessState": "blocked",
      "riskSummary": {
        "highestSeverity": "high",
        "marketsWithFlags": 2,
        "blockedMarkets": 2,
        "maxSettlementLagMinutes": 198,
        "maxAbsProbabilityMovePctPoints": 25.97,
        "primaryBlockingFlagCodes": [
          "EVENT_MARKET_MISMATCH",
          "LARGE_ODDS_MOVE",
          "SETTLEMENT_DRIFT"
        ]
      },
      "topRecommendedActions": [
        "EVENT_MARKET_MISMATCH",
        "SETTLEMENT_DRIFT",
        "LARGE_ODDS_MOVE"
      ],
      "topFlagCodes": [
        "EVENT_MARKET_MISMATCH",
        "LARGE_ODDS_MOVE",
        "LARGE_ODDS_MOVE",
        "LARGE_ODDS_MOVE",
        "LARGE_ODDS_MOVE"
      ]
    },
    "txoddsCapture": {
      "generatedAt": "2026-06-26T06:20:00.000Z",
      "matchCount": 1,
      "marketCount": 1,
      "flagCount": 2,
      "riskScore": 5,
      "recommendedActionCount": 2,
      "automationReadinessState": "blocked",
      "riskSummary": {
        "highestSeverity": "high",
        "marketsWithFlags": 1,
        "blockedMarkets": 1,
        "maxSettlementLagMinutes": null,
        "maxAbsProbabilityMovePctPoints": 8.4,
        "primaryBlockingFlagCodes": [
          "LARGE_ODDS_MOVE"
        ]
      },
      "topRecommendedActions": [
        "LARGE_ODDS_MOVE",
        "STALE_FEED"
      ],
      "topFlagCodes": [
        "LARGE_ODDS_MOVE",
        "STALE_FEED"
      ]
    }
  },
  "artifacts": [
    {
      "path": "public/index.html",
      "description": "Static public MVP HTML",
      "sha256": "ba74d666032d8b57937fb46d95df018a54ee40ea9cc8a66dffa80905100c3542",
      "sizeBytes": 19934
    },
    {
      "path": "public/judge-brief.html",
      "description": "Public judge evaluation brief",
      "sha256": "06589ef0b42806df02d454a7ee692a1ef5fd872000555222928b0d1fb686fb9b",
      "sizeBytes": 14743
    },
    {
      "path": "public/compliance.html",
      "description": "Public hackathon compliance note",
      "sha256": "f871c2125a42c17e229af365015277a1b16eff9234c8e3ffc12ca0a9f1d55fbe",
      "sizeBytes": 5931
    },
    {
      "path": "public/demo-video.html",
      "description": "Public demo video review page",
      "sha256": "6df4ceeb2b7cc06c00926db68cf8a28a2fd6414aeebfc471c538d44d578b10fc",
      "sizeBytes": 4892
    },
    {
      "path": "public/judge-playground.html",
      "description": "Public paste-in TxODDS judge playground",
      "sha256": "aeba25d893bb12d799328bbca78f99c82bba2aa397f097b1479a170602596cee",
      "sizeBytes": 7973
    },
    {
      "path": "public/playground.js",
      "description": "Browser-only playground analyzer runtime",
      "sha256": "c020f65fdae7160de65d828c946d25be1ceabbaab1fe1e3884560d0df641d9b7",
      "sizeBytes": 19213
    },
    {
      "path": "src/browser-playground.js",
      "description": "Source for the browser-only playground runtime",
      "sha256": "c020f65fdae7160de65d828c946d25be1ceabbaab1fe1e3884560d0df641d9b7",
      "sizeBytes": 19213
    },
    {
      "path": "public/report.json",
      "description": "Machine-readable fixture analyzer report",
      "sha256": "a664eb254ea56b5985964af0eebe626084f7d75e8ed28b7738610b6cfaf98ea5",
      "sizeBytes": 11562,
      "summary": {
        "generatedAt": "2026-06-26T06:20:00.000Z",
        "matchCount": 2,
        "marketCount": 2,
        "flagCount": 10,
        "riskScore": 35,
        "recommendedActionCount": 4,
        "automationReadinessState": "blocked",
        "riskSummary": {
          "highestSeverity": "high",
          "marketsWithFlags": 2,
          "blockedMarkets": 2,
          "maxSettlementLagMinutes": 198,
          "maxAbsProbabilityMovePctPoints": 25.97,
          "primaryBlockingFlagCodes": [
            "EVENT_MARKET_MISMATCH",
            "LARGE_ODDS_MOVE",
            "SETTLEMENT_DRIFT"
          ]
        },
        "topRecommendedActions": [
          "EVENT_MARKET_MISMATCH",
          "SETTLEMENT_DRIFT",
          "LARGE_ODDS_MOVE"
        ],
        "topFlagCodes": [
          "EVENT_MARKET_MISMATCH",
          "LARGE_ODDS_MOVE",
          "LARGE_ODDS_MOVE",
          "LARGE_ODDS_MOVE",
          "LARGE_ODDS_MOVE"
        ]
      }
    },
    {
      "path": "fixtures/sample-worldcup-feed.json",
      "description": "Replayable fixture-shaped World Cup feed",
      "sha256": "e192f41e285a665fc45dfd196433f8e76bf9ac55493b63255c7803b56fe465dd",
      "sizeBytes": 2714
    },
    {
      "path": "public/txodds-capture-report.json",
      "description": "Machine-readable captured TxODDS-shaped payload report",
      "sha256": "8b2b447fac3502347b28024cb2cd6da9b8de75f5e1a4bd36856534bf3e9a94f5",
      "sizeBytes": 4568,
      "summary": {
        "generatedAt": "2026-06-26T06:20:00.000Z",
        "matchCount": 1,
        "marketCount": 1,
        "flagCount": 2,
        "riskScore": 5,
        "recommendedActionCount": 2,
        "automationReadinessState": "blocked",
        "riskSummary": {
          "highestSeverity": "high",
          "marketsWithFlags": 1,
          "blockedMarkets": 1,
          "maxSettlementLagMinutes": null,
          "maxAbsProbabilityMovePctPoints": 8.4,
          "primaryBlockingFlagCodes": [
            "LARGE_ODDS_MOVE"
          ]
        },
        "topRecommendedActions": [
          "LARGE_ODDS_MOVE",
          "STALE_FEED"
        ],
        "topFlagCodes": [
          "LARGE_ODDS_MOVE",
          "STALE_FEED"
        ]
      }
    },
    {
      "path": "fixtures/sample-txodds-capture.json",
      "description": "Captured TxODDS-shaped JSON fixture",
      "sha256": "4758a867827167ac26d355923182d7b5efa84a0921ff790439e03093c4de27a4",
      "sizeBytes": 1516
    },
    {
      "path": "src/normalize-txodds.js",
      "description": "Offline TxODDS-shaped payload normalizer",
      "sha256": "9b54da3ee71fc0ef053b21104b78e19a1a9b47c0de9063b5d65397460434373e",
      "sizeBytes": 5174
    },
    {
      "path": "src/analyze.js",
      "description": "Dependency-free odds and settlement analyzer",
      "sha256": "df74f0c6c03d20fa9de5633c47e18ef67c8319cd3bd7599b65574139d5b0be72",
      "sizeBytes": 14626
    },
    {
      "path": "src/render-html.js",
      "description": "Static HTML renderer",
      "sha256": "9e8bc3adb0c00c9e669aaed5444844962669330eabd3a88702fb278b1e00f7a4",
      "sizeBytes": 48134
    },
    {
      "path": "package.json",
      "description": "Node scripts and reproducible build entrypoints",
      "sha256": "0a8441ec4b6e8931e87a7e141e99b22ba26bb56abcddc23a8390a7729cc030d2",
      "sizeBytes": 1469
    },
    {
      "path": ".github/workflows/verify.yml",
      "description": "GitHub Actions public packet verification workflow",
      "sha256": "3665b3c38e94d9906c663591f18c6dd6b31956838af3c18e84b206908f5d76c5",
      "sizeBytes": 1273
    },
    {
      "path": "SUBMISSION.md",
      "description": "Superteam field packet",
      "sha256": "d71894f1f20e9021d9ff46f43316119c2caec44b04aef8c9e92966af90de1582",
      "sizeBytes": 5747
    },
    {
      "path": "REVIEW.md",
      "description": "Judge review checklist",
      "sha256": "b92bde0e73caa0d495138ece6d4052c84422e1a34f35323132300bfa42c12e80",
      "sizeBytes": 3641
    },
    {
      "path": "public/.well-known/ai.txt",
      "description": "AI-readable public review manifest",
      "sha256": "f5e3ee412792df895c8da08dfed350ea85aa07ec9a71d0401bcd736c72d6dc9b",
      "sizeBytes": 2109
    },
    {
      "path": "src/verify-packet.js",
      "description": "Local public-packet verifier",
      "sha256": "b69b28c5d4f7d82c8e31ea2b1763a6dcf601c5c02e2435e267d3ece07927a57e",
      "sizeBytes": 6365
    }
  ],
  "safety": {
    "noPrivateKeys": true,
    "noSeedPhrases": true,
    "noApiTokens": true,
    "noWalletConnectionRequired": true,
    "noJudgeWalletOrAccountRequired": true,
    "noPaidSubscriptionRequiredForReview": true,
    "noNetworkCallsInBuild": true,
    "liveTxOddsCallsIncluded": false
  }
}
